kopl_engine/__init__.py
kopl_engine/engine.py
kopl_engine/libKoPL.so
kopl_engine-0.1.1.dist-info/LICENSE
kopl_engine-0.1.1.dist-info/METADATA
kopl_engine-0.1.1.dist-info/WHEEL
kopl_engine-0.1.1.dist-info/top_level.txt
kopl_engine-0.1.1.dist-info/RECORD
